youqu_pms_driver/__init__.py
youqu_pms_driver/__version__.py
youqu_pms_driver/cli.py
youqu_pms_driver/send2pms.py
youqu_pms_driver/suite.py
youqu_pms_driver/task.py
youqu_pms_driver-2024.6.23.dist-info/METADATA
youqu_pms_driver-2024.6.23.dist-info/WHEEL
youqu_pms_driver-2024.6.23.dist-info/entry_points.txt
youqu_pms_driver-2024.6.23.dist-info/licenses/LICENSE
youqu_pms_driver-2024.6.23.dist-info/RECORD
